psbtree/__init__.cpython-310-x86_64-linux-gnu.so
psbtree/__init__.pyi
psbtree/core.cpython-310-x86_64-linux-gnu.so
psbtree/core.pyi
psbtree/libbehaviortree_cpp.so
psbtree/engine/__init__.cpython-310-x86_64-linux-gnu.so
psbtree/engine/__init__.pyi
psbtree/engine/cyclic_engine.cpython-310-x86_64-linux-gnu.so
psbtree/engine/cyclic_engine.pyi
psbtree/engine/cyclic_engine_scheduler.cpython-310-x86_64-linux-gnu.so
psbtree/engine/parallel_cyclic_engine.cpython-310-x86_64-linux-gnu.so
psbtree/engine/parallel_cyclic_engine.pyi
psbtree/engine/parallel_engine.cpython-310-x86_64-linux-gnu.so
psbtree/engine/parallel_engine.pyi
psbtree/engine/sequential_engine.cpython-310-x86_64-linux-gnu.so
psbtree/engine/sequential_engine.pyi
psbtree/engine/thread_engine.cpython-310-x86_64-linux-gnu.so
psbtree/engine/thread_engine.pyi
psbtree/engine/cyclic/base.cpython-310-x86_64-linux-gnu.so
psbtree/engine/cyclic/base.pyi
psbtree/engine/cyclic/mprocess.cpython-310-x86_64-linux-gnu.so
psbtree/engine/cyclic/mprocess.pyi
psbtree/engine/trigger/async_base.cpython-310-x86_64-linux-gnu.so
psbtree/engine/trigger/base.cpython-310-x86_64-linux-gnu.so
psbtree/engine/trigger/base.pyi
psbtree/engine/trigger/mthread.cpython-310-x86_64-linux-gnu.so
psbtree/engine/trigger/mthread.pyi
psbtree/nodes/__init__.cpython-310-x86_64-linux-gnu.so
psbtree/nodes/__init__.pyi
psbtree/nodes/action_node.cpython-310-x86_64-linux-gnu.so
psbtree/nodes/action_node.pyi
psbtree/nodes/common_nodes.cpython-310-x86_64-linux-gnu.so
psbtree/nodes/common_nodes.pyi
psbtree/nodes/condition_nodes.cpython-310-x86_64-linux-gnu.so
psbtree/nodes/condition_nodes.pyi
psbtree/nodes/control_nodes.cpython-310-x86_64-linux-gnu.so
psbtree/nodes/control_nodes.pyi
psbtree/nodes/decorator_nodes.cpython-310-x86_64-linux-gnu.so
psbtree/nodes/decorator_nodes.pyi
psbtree/plugins/__init__.cpython-310-x86_64-linux-gnu.so
psbtree/plugins/__init__.pyi
psbtree/plugins/agno/__init__.cpython-310-x86_64-linux-gnu.so
psbtree-0.1.32.dist-info/METADATA
psbtree-0.1.32.dist-info/WHEEL
psbtree-0.1.32.dist-info/entry_points.txt
psbtree-0.1.32.dist-info/top_level.txt
psbtree-0.1.32.dist-info/RECORD
psbtree-0.1.32.dist-info/licenses/LICENSE.txt
