Metadata-Version: 2.4
Name: psbtree
Version: 0.1.32
Summary: Python Behavior Tree Framework with C++ Core
Author: Your Name
Author-email: iepanda <iepanda@outlook.com>
Maintainer-email: PulSpread <iepanda@outlook.com>
License-Expression: MIT
Keywords: behavior-tree,ai,decision-tree,python,cpp
Classifier: Development Status :: 3 - Alpha
Classifier: Intended Audience :: Developers
Classifier: Topic :: Software Development :: Build Tools
Classifier: Programming Language :: Python :: 3
Classifier: Programming Language :: Python :: 3.9
Classifier: Programming Language :: Python :: 3.10
Classifier: Programming Language :: Python :: 3.11
Classifier: Programming Language :: Python :: 3.12
Classifier: Programming Language :: Python :: 3.13
Classifier: Programming Language :: Python :: 3 :: Only
Requires-Python: >=3.9
License-File: LICENSE.txt
Requires-Dist: loguru>=0.7.2
Requires-Dist: psdec>=0.1.1
Provides-Extra: cuda
Requires-Dist: pycuda>=2023.1; extra == "cuda"
Requires-Dist: numpy>=1.24.0; extra == "cuda"
Provides-Extra: dev
Requires-Dist: check-manifest>=0.48.0; extra == "dev"
Requires-Dist: Cython>=3.0.0; extra == "dev"
Provides-Extra: test
Requires-Dist: coverage>=7.3.0; extra == "test"
Requires-Dist: pytest>=7.4.0; extra == "test"
Requires-Dist: pytest-mock>=3.11.1; extra == "test"
Dynamic: author
Dynamic: license-file
